tag_commit/__init__.py
tag_commit/cli.py
tag_commit/lib.py
tag_commit/logging.py
tag_commit/settings.py
dycw_tag_commit-0.5.1.dist-info/WHEEL
dycw_tag_commit-0.5.1.dist-info/entry_points.txt
dycw_tag_commit-0.5.1.dist-info/METADATA
dycw_tag_commit-0.5.1.dist-info/RECORD
