Metadata-Version: 2.3
Name: dycw-tag-commit
Version: 0.5.1
Summary: Tag the latest commit with the version read from `bump-my-version`
Author: Derek Wan
Author-email: Derek Wan <d.wan@icloud.com>
Requires-Dist: click>=8.3.1,<8.4
Requires-Dist: dycw-utilities>=0.170.0,<0.171
Requires-Dist: rich>=14.2.0,<14.3
Requires-Dist: typed-settings[attrs,click]>=25.3.0,<25.4
Requires-Python: >=3.13
